pywebchannel/CodeAnalyzer.py
pywebchannel/Controller.py
pywebchannel/GeneratorWatcher.py
pywebchannel/HttpServer.py
pywebchannel/Utils.py
pywebchannel/WebChannelService.py
pywebchannel/__init__.py
pywebchannel/files_in_user_project/backend/ts_generator.py
pywebchannel/files_in_user_project/frontend/src/api/BaseAPI.ts
pywebchannel/files_in_user_project/frontend/src/api/CommandAPI.ts
pywebchannel/files_in_user_project/frontend/src/api/controllers/controllers.txt
pywebchannel/files_in_user_project/frontend/src/api/models/Response.ts
pywebchannel/files_in_user_project/frontend/src/api/models/Signal.ts
pywebchannel/files_in_user_project/frontend/src/api/qwebchannel/index.d.ts
pywebchannel/files_in_user_project/frontend/src/api/qwebchannel/index.js
pywebchannel/files_in_user_project/frontend/src/api/utils/Utils.ts
pywebchannel-1.9.dist-info/METADATA
pywebchannel-1.9.dist-info/WHEEL
pywebchannel-1.9.dist-info/licenses/LICENSE
pywebchannel-1.9.dist-info/RECORD
