Metadata-Version: 2.1
Name: pywebchannel
Version: 1.9
Summary: This repository generates auto typescript files for QWebChannel python local backend. It enables you to build a stunning UI for your python project with web technologies.
Project-URL: GitHub, https://github.com/cihanuyanik/pywebchannel
Project-URL: Doc. & API, https://pywebchannel.readthedocs.io/
Project-URL: Issues, https://github.com/cihanuyanik/pywebchannel/issues
Author-email: Cihan Uyanik <cihanuyanik34@gmail.com>
License-File: LICENSE
Classifier: License :: OSI Approved :: MIT License
Classifier: Operating System :: OS Independent
Classifier: Programming Language :: Python :: 3
Requires-Python: >=3.8
Requires-Dist: colorama
Requires-Dist: pydantic
Requires-Dist: pyside6
